voicevox_python/__init__.py
voicevox_python/model.py
voicevox_python/py.typed
voicevox_python/query.py
voicevox_python/speaker.py
voicevox_python-2023.9.7.9.34.dist-info/METADATA
voicevox_python-2023.9.7.9.34.dist-info/WHEEL
voicevox_python-2023.9.7.9.34.dist-info/licenses/LICENSE
voicevox_python-2023.9.7.9.34.dist-info/RECORD
