Metadata-Version: 2.1
Name: voicevox-python
Version: 2023.9.7.9.34
Summary: API wrapper for voicevox
Project-URL: Homepage, https://github.com/Nakanishi123/voicevox-python
Author-email: Nakanishi <45790603+Nakanishi123@users.noreply.github.com>
License-Expression: CC0-1.0
License-File: LICENSE
Classifier: License :: CC0 1.0 Universal (CC0 1.0) Public Domain Dedication
Classifier: Programming Language :: Python :: 3
Requires-Python: >=3.8
Requires-Dist: pydantic>=2
Requires-Dist: requests>=2
